{
  "products": [
    {
      "id": "cgklVa",
      "name": "Cerveza Napoli",
      "description": "La peor cerveza italiana",
      "price": 25
    },
    {
      "id": "renZWL",
      "name": "Burritos",
      "description": "Burritos belicos",
      "price": 13
    },
    {
      "id": "uLwzQd",
      "name": "Chiva Cola",
      "description": "La mejor soda del mundo",
      "price": 0.5
    },
    {
      "id": "NSoROQ",
      "name": "Squirt",
      "description": "Refresco sabor limón",
      "price": "15"
    }
  ]
}